{
  "property_id": 10193824,
  "gen_id": "GEN-10193824",
  "property_name": "Studio Ibirapuera 212 -Estacionamento, Gym, Wi-Fi",
  "property_slug": "studio-ibirapuera-212-estacionamento-gym-wi-fi",
  "country_code": "BR",
  "currency": "BRL",
  "star_rating": 4.0,
  "review_score": 8.4,
  "published": true,
  "data_quality_flag": "GOOD",
  "total_reviews": 1,
  "reviews": [
    {
      "review_id": 5105749026,
      "review_date": "2024-11-22",
      "review_year": 2024,
      "score": 8.0,
      "language": "en-us",
      "summary": null,
      "positive": null,
      "negative": null,
      "reviewer_name": "Corrêa",
      "reviewer_country": "br",
      "reviewer_travel_purpose": "business",
      "reviewer_type": "solo_traveller"
    }
  ]
}